gcd/chisel/verilog_generated/RealGCD.v
module RealGCD(
  input         clock,
  input         reset,
  output        io_in_ready,
  input         io_in_valid,
  input  [15:0] io_in_bits_a,
  input  [15:0] io_in_bits_b,
  output        io_out_valid,
  output [15:0] io_out_bits
);
  reg [15:0] a; // @[RealGCD.scala 22:14]
  reg [31:0] _RAND_0;
  reg [15:0] b; // @[RealGCD.scala 23:14]
  reg [31:0] _RAND_1;
  reg  p; // @[RealGCD.scala 24:18]
  reg [31:0] _RAND_2;
  
  wire  _T_30; // @[RealGCD.scala 26:18]
  wire  _T_33; // @[RealGCD.scala 28:21]
  wire [15:0] _GEN_0; // @[RealGCD.scala 28:28]
  wire [15:0] _GEN_1; // @[RealGCD.scala 28:28]
  wire  _GEN_2; // @[RealGCD.scala 28:28]
  wire  _T_35; // @[RealGCD.scala 35:13]
  wire [16:0] _T_36; // @[RealGCD.scala 36:28]
  wire [16:0] _T_37; // @[RealGCD.scala 36:28]
  wire [15:0] _T_38; // @[RealGCD.scala 36:28]
  wire [15:0] _GEN_3; // @[RealGCD.scala 35:19]
  wire [15:0] _GEN_4; // @[RealGCD.scala 35:19]
  wire  _T_40; // @[RealGCD.scala 40:21]
  wire  _GEN_7; // @[RealGCD.scala 41:23]
  
  assign _T_30 = p == 1'h0; // @[RealGCD.scala 26:18]
  assign _T_33 = io_in_valid & _T_30; // @[RealGCD.scala 28:21]
  assign _GEN_0 = _T_33 ? io_in_bits_a : a; // @[RealGCD.scala 28:28]
  assign _GEN_1 = _T_33 ? io_in_bits_b : b; // @[RealGCD.scala 28:28]
  assign _GEN_2 = _T_33 ? 1'h1 : p; // @[RealGCD.scala 28:28]
  assign _T_35 = a > b; // @[RealGCD.scala 35:13]
  assign _T_36 = b - a; // @[RealGCD.scala 36:28]
  assign _T_37 = $unsigned(_T_36); // @[RealGCD.scala 36:28]
  assign _T_38 = _T_37[15:0]; // @[RealGCD.scala 36:28]
  assign _GEN_3 = _T_35 ? b : _GEN_0; // @[RealGCD.scala 35:19]
  assign _GEN_4 = _T_35 ? a : _T_38; // @[RealGCD.scala 35:19]
  assign _T_40 = b == 16'h0; // @[RealGCD.scala 40:21]
  assign _GEN_7 = io_out_valid ? 1'h0 : _GEN_2; // @[RealGCD.scala 41:23]
  assign io_in_ready = p == 1'h0; // @[RealGCD.scala 26:15]
  assign io_out_valid = _T_40 & p; // @[RealGCD.scala 40:16]
  assign io_out_bits = a; // @[RealGCD.scala 39:16]

  always @(posedge clock) begin
    if (p) begin
      if (_T_35) begin
        a <= b;
      end else begin
        if (_T_33) begin
          a <= io_in_bits_a;
        end
      end
    end else begin
      if (_T_33) begin
        a <= io_in_bits_a;
      end
    end
    if (p) begin
      if (_T_35) begin
        b <= a;
      end else begin
        b <= _T_38;
      end
    end else begin
      if (_T_33) begin
        b <= io_in_bits_b;
      end
    end
    if (reset) begin
      p <= 1'h0;
    end else begin
      if (io_out_valid) begin
        p <= 1'h0;
      end else begin
        if (_T_33) begin
          p <= 1'h1;
        end
      end
    end
  end
endmodule

gcd/chisel/verilog_generated/RealGCD.vcd
$version Generated by VerilatedVcd $end
$date Sun Jan 17 10:32:55 2021
 $end
$timescale 1ps $end

 $scope module TOP $end
  $var wire  1 & clock $end
  $var wire 16 * io_in_bits_a [15:0] $end
  $var wire 16 + io_in_bits_b [15:0] $end
  $var wire  1 ( io_in_ready $end
  $var wire  1 ) io_in_valid $end
  $var wire 16 - io_out_bits [15:0] $end
  $var wire  1 , io_out_valid $end
  $var wire  1 ' reset $end
  $scope module RealGCD $end
   $var wire 16 # a [15:0] $end
   $var wire 16 $ b [15:0] $end
   $var wire  1 & clock $end
   $var wire 16 * io_in_bits_a [15:0] $end
   $var wire 16 + io_in_bits_b [15:0] $end
   $var wire  1 ( io_in_ready $end
   $var wire  1 ) io_in_valid $end
   $var wire 16 - io_out_bits [15:0] $end
   $var wire  1 , io_out_valid $end
   $var wire  1 % p $end
   $var wire  1 ' reset $end
  $upscope $end
 $upscope $end
$enddefinitions $end


#0
b0000000000000000 #
b0000000000000000 $
0%
0&
1'
1(
0)
b0000000000000000 *
b0000000000000000 +
0,
b0000000000000000 -
#1
1&
#2
0&
#3
1&
#4
0&
#5
1&
#6
0&
#7
1&
#8
0&
#9
1&
#10
0&
0'
1)
b0000000000110000 *
b0000000000100000 +
#11
b0000000000110000 #
b0000000000100000 $
1%
1&
0(
b0000000000110000 -
#12
0&
0)
#13
b0000000000100000 #
b0000000000110000 $
1&
b0000000000100000 -
#14
0&
#15
b0000000000010000 $
1&
#16
0&
#17
b0000000000010000 #
b0000000000100000 $
1&
b0000000000010000 -
#18
0&
#19
b0000000000010000 $
1&
#20
0&
#21
b0000000000000000 $
1&
1,
#22
0&
1)
b0000000000000111 *
b0000000000000011 +
#23
b0000000000000000 #
b0000000000010000 $
0%
1&
1(
0,
b0000000000000000 -
#24
0&
#25
b0000000000000111 #
b0000000000000011 $
1%
1&
0(
b0000000000000111 -
#26
0&
0)
#27
b0000000000000011 #
b0000000000000111 $
1&
b0000000000000011 -
#28
0&
#29
b0000000000000100 $
1&
#30
0&
#31
b0000000000000001 $
1&
#32
0&
#33
b0000000000000001 #
b0000000000000011 $
1&
b0000000000000001 -
#34
0&
#35
b0000000000000010 $
1&
#36
0&
#37
b0000000000000001 $
1&
#38
0&
#39
b0000000000000000 $
1&
1,
#40
0&
1)
b0000000001100100 *
b0000000000001010 +
#41
b0000000000000000 #
b0000000000000001 $
0%
1&
1(
0,
b0000000000000000 -
#42
0&
#43
b0000000001100100 #
b0000000000001010 $
1%
1&
0(
b0000000001100100 -
#44
0&
0)
#45
b0000000000001010 #
b0000000001100100 $
1&
b0000000000001010 -
#46
0&
#47
b0000000001011010 $
1&
#48
0&
#49
b0000000001010000 $
1&
#50
0&
#51
b0000000001000110 $
1&
#52
0&
#53
b0000000000111100 $
1&
#54
0&
#55
b0000000000110010 $
1&
#56
0&
#57
b0000000000101000 $
1&
#58
0&
#59
b0000000000011110 $
1&
#60
0&
#61
b0000000000010100 $
1&
#62
0&
#63
b0000000000001010 $
1&
#64
0&
#65
b0000000000000000 $
1&
1,
