gcd/verilog/RealGCD.v
module RealGCD(
  input         clock,
  input         reset,
  output        io_in_ready,
  input         io_in_valid,
  input  [15:0] io_in_bits_a,
  input  [15:0] io_in_bits_b,
  output        io_out_valid,
  output [15:0] io_out_bits
);
  reg [15:0] a;
  reg [15:0] b;
  reg  busy;
  wire  allow_enter;
  wire  gt;
  wire [15:0] sub;
  assign allow_enter = io_in_valid & !busy;
  assign gt = a > b;
  assign sub = b - a;
  assign io_in_ready = !busy;
  assign io_out_valid = (b == 16'h0) & busy;
  assign io_out_bits = a;

  always @(posedge clock) begin
    
    if (reset) begin
      a <= 16'h0;
    end else begin
      if (io_out_valid) begin
        a <= 16'h0;
      end else begin
        if (busy) begin
          if (gt) begin
            a <= b;
          end else begin
            if (allow_enter) begin
              a <= io_in_bits_a;
            end
          end
        end else begin
          if (allow_enter) begin
            a <= io_in_bits_a;
          end
        end
      end
    end
    
    if (reset) begin
      b <= 16'h0;
    end else begin
      if (io_out_valid) begin
        b <= 16'h0;
      end else begin
        if (busy) begin
          if (gt) begin
            b <= a;
          end else begin
            b <= sub;
          end
        end else begin
          if (allow_enter) begin
            b <= io_in_bits_b;
          end
        end
      end
    end
    
    if (reset) begin
      busy <= 1'h0;
    end else begin
      if (io_out_valid) begin
        busy <= 1'h0;
      end else begin
        if (allow_enter) begin
          busy <= 1'h1;
        end
      end
    end
  
  end
endmodule

gcd/verilog/testbench.v
`include "RealGCD.v"

module testbench;
reg bench_clk;
reg bench_rst;
reg bench_io_in_valid;
reg [15:0]bench_io_in_bits_a;
reg [15:0]bench_io_in_bits_b;
wire bench_io_in_ready;
wire bench_io_out_valid;
wire [15:0]bench_io_out_bits;


event e_clk;


initial begin
    $dumpfile("testbench.vcd");
    $dumpvars(0, dut);
    // $fsdbDumpfile("testbench.fsdb");
    // $fsdbDumpvars(0, dut);

end
initial
begin
#0 bench_clk = 1'b0;
end

always
begin
#10 bench_clk = !bench_clk;
->e_clk;
end

initial
begin
#0 bench_rst = 1'b1;
#20 bench_rst = 1'b0;
end

RealGCD dut(
.clock(bench_clk),
.reset(bench_rst),
.io_in_valid(bench_io_in_valid),
.io_in_bits_a(bench_io_in_bits_a),
.io_in_bits_b(bench_io_in_bits_b),
.io_in_ready(bench_io_in_ready),
.io_out_valid(bench_io_out_valid),
.io_out_bits(bench_io_out_bits)
);

initial
begin
$monitor($time, " reset = %b, clock = %b , io_in_valid = %b , io_in_bits_a = %b , io_in_bits_b = %b , io_in_ready = %b , io_out_valid = %b , io_out_bits = %b ",
bench_rst, bench_clk, bench_io_in_valid, bench_io_in_bits_a, bench_io_in_bits_b, bench_io_in_ready, bench_io_out_valid, bench_io_out_bits);
end

initial
begin
#40 
bench_io_in_valid = 1;
bench_io_in_bits_a = 48;
bench_io_in_bits_b = 32;
#20 bench_io_in_valid = 0;

#200 
bench_io_in_valid = 1;
bench_io_in_bits_a = 7;
bench_io_in_bits_b = 3;
#20 bench_io_in_valid = 0;

#200 
bench_io_in_valid = 1;
bench_io_in_bits_a = 100;
bench_io_in_bits_b = 10;
#20 bench_io_in_valid = 0;
#400 $finish;
end

endmodule

gcd/verilog/testbench.vcd
$date
	Tue Jan 19 22:44:57 2021
$end
$version
	Icarus Verilog
$end
$timescale
	1s
$end
$scope module testbench $end
$scope module dut $end
$var wire 1 ! allow_enter $end
$var wire 1 " clock $end
$var wire 16 # io_in_bits_a [15:0] $end
$var wire 16 $ io_in_bits_b [15:0] $end
$var wire 1 % io_in_valid $end
$var wire 16 & io_out_bits [15:0] $end
$var wire 1 ' io_out_valid $end
$var wire 1 ( reset $end
$var wire 16 ) sub [15:0] $end
$var wire 1 * io_in_ready $end
$var wire 1 + gt $end
$var reg 16 , a [15:0] $end
$var reg 16 - b [15:0] $end
$var reg 1 . busy $end
$upscope $end
$upscope $end
$enddefinitions $end
#0
$dumpvars
x.
bx -
bx ,
x+
x*
bx )
1(
x'
bx &
x%
bx $
bx #
0"
x!
$end
#10
0'
1*
0.
0+
b0 )
b0 -
b0 &
b0 ,
1"
#20
0"
0(
#30
1"
#40
1!
0"
b100000 $
b110000 #
1%
#50
0!
0*
1.
b100000 -
1+
b1111111111110000 )
b110000 &
b110000 ,
1"
#60
0"
0%
#70
b110000 -
0+
b10000 )
b100000 &
b100000 ,
1"
#80
0"
#90
1+
b1111111111110000 )
b10000 -
1"
#100
0"
#110
b100000 -
0+
b10000 )
b10000 &
b10000 ,
1"
#120
0"
#130
b0 )
b10000 -
1"
#140
0"
#150
1'
1+
b1111111111110000 )
b0 -
1"
#160
0"
#170
0'
1*
0.
0+
b0 )
b0 &
b0 ,
1"
#180
0"
#190
1"
#200
0"
#210
1"
#220
0"
#230
1"
#240
0"
#250
1"
#260
1!
0"
b11 $
b111 #
1%
#270
0!
0*
1.
b11 -
1+
b1111111111111100 )
b111 &
b111 ,
1"
#280
0"
0%
#290
b111 -
0+
b100 )
b11 &
b11 ,
1"
#300
0"
#310
b1 )
b100 -
1"
#320
0"
#330
1+
b1111111111111110 )
b1 -
1"
#340
0"
#350
b11 -
0+
b10 )
b1 &
b1 ,
1"
#360
0"
#370
b1 )
b10 -
1"
#380
0"
#390
b0 )
b1 -
1"
#400
0"
#410
1'
1+
b1111111111111111 )
b0 -
1"
#420
0"
#430
0'
1*
0.
0+
b0 )
b0 &
b0 ,
1"
#440
0"
#450
1"
#460
0"
#470
1"
#480
1!
0"
b1010 $
b1100100 #
1%
#490
0!
0*
1.
b1010 -
1+
b1111111110100110 )
b1100100 &
b1100100 ,
1"
#500
0"
0%
#510
b1100100 -
0+
b1011010 )
b1010 &
b1010 ,
1"
#520
0"
#530
b1010000 )
b1011010 -
1"
#540
0"
#550
b1000110 )
b1010000 -
1"
#560
0"
#570
b111100 )
b1000110 -
1"
#580
0"
#590
b110010 )
b111100 -
1"
#600
0"
#610
b101000 )
b110010 -
1"
#620
0"
#630
b11110 )
b101000 -
1"
#640
0"
#650
b10100 )
b11110 -
1"
#660
0"
#670
b1010 )
b10100 -
1"
#680
0"
#690
b0 )
b1010 -
1"
#700
0"
#710
1'
1+
b1111111111110110 )
b0 -
1"
#720
0"
#730
0'
1*
0.
0+
b0 )
b0 &
b0 ,
1"
